request_lifecycle/__init__.py
request_lifecycle/logger.py
request_lifecycle/request_lifecycle.py
request_lifecycle/time_util.py
request_lifecycle-1.1.3.dist-info/METADATA
request_lifecycle-1.1.3.dist-info/WHEEL
request_lifecycle-1.1.3.dist-info/top_level.txt
request_lifecycle-1.1.3.dist-info/RECORD
