Metadata-Version: 2.1
Name: request-lifecycle
Version: 1.1.3
Summary: Request lifecycle logger for flask
Home-page: http://git.azure.gagogroup.cn/efficiency/request-lifecyle-logger-python
Author: Frank Lin
Author-email: lin.xiaoe.f@gmail.com
License: UNKNOWN
Platform: UNKNOWN
Classifier: Programming Language :: Python :: 3.6
Classifier: Framework :: Flask
Requires-Python: >3.6.0
Requires-Dist: Flask (>=0.12.2)
Requires-Dist: requests (>=2.18.4)
